Metadata-Version: 2.1
Name: finite-topology
Version: 0.1.6
Summary: A Python library for defining and manipulating topologies on finite sets.
Home-page: https://github.com/nand0san/Topology
Author: nand0san
Author-email: hancaidolosdos@hotmail.com
Project-URL: Source, https://github.com/nand0san/Topology
Project-URL: Tracker, https://github.com/nand0san/Topology/issues
Keywords: topology,mathematics,finite sets,discrete topology
Classifier: Development Status :: 3 - Alpha
Classifier: Intended Audience :: Education
Classifier: Intended Audience :: Science/Research
Classifier: License :: OSI Approved :: MIT License
Classifier: Programming Language :: Python :: 3
Classifier: Programming Language :: Python :: 3.7
Classifier: Programming Language :: Python :: 3.8
Classifier: Programming Language :: Python :: 3.9
Classifier: Programming Language :: Python :: 3.10
Classifier: Topic :: Scientific/Engineering :: Mathematics
Requires-Python: >=3.7
License-File: LICENSE
